geny/__init__.py
geny/cli/__init__.py
geny/cli/cli.py
geny/commands/__init__.py
geny/commands/callbacks.py
geny/commands/destroy/__init__.py
geny/commands/destroy/dockerfile.py
geny/commands/destroy/main.py
geny/commands/destroy/template.py
geny/commands/generate/dockerfile.py
geny/commands/generate/main.py
geny/commands/generate/template.py
geny/core/__init__.py
geny/core/logger.py
geny/core/utils.py
geny/core/decorators/__init__.py
geny/core/decorators/error_handler.py
geny/core/decorators/singleton.py
geny/core/filesystem/__init__.py
geny/core/filesystem/directories.py
geny/core/filesystem/files.py
geny/core/filesystem/filesystem.py
geny/core/filesystem/finder.py
geny/core/filesystem/protocols.py
geny/core/filesystem/transformations.py
geny/core/templates/__init__.py
geny/core/templates/protocols.py
geny/core/templates/template.py
geny/extensions/__init__.py
geny/extensions/aliased.py
geny/extensions/combined.py
geny/extensions/discoverable.py
geny/template_files/__init__.py
geny-0.1.8.dist-info/LICENSE
geny-0.1.8.dist-info/METADATA
geny-0.1.8.dist-info/WHEEL
geny-0.1.8.dist-info/entry_points.txt
geny-0.1.8.dist-info/top_level.txt
geny-0.1.8.dist-info/RECORD
