Metadata-Version: 2.2
Name: geny
Version: 0.1.8
Summary: An extendable file generator
Author-email: Leo Neto <leo@ekletik.com>
Maintainer-email: Leo Neto <leo@ekletik.com>
License: BSD 3-Clause License
Project-URL: Homepage, https://github.com/oleoneto/geny
Project-URL: Issues, https://github.com/oleoneto/geny/issues
Keywords: automation,files,generators
Classifier: Development Status :: 4 - Beta
Classifier: Environment :: Web Environment
Classifier: Intended Audience :: Developers
Classifier: License :: OSI Approved :: BSD License
Classifier: Natural Language :: English
Classifier: Operating System :: OS Independent
Classifier: Programming Language :: Python
Classifier: Programming Language :: Python :: 3
Classifier: Programming Language :: Python :: 3.6
Classifier: Programming Language :: Python :: 3.7
Classifier: Programming Language :: Python :: 3.8
Classifier: Programming Language :: Python :: 3.9
Classifier: Programming Language :: Python :: 3.10
Classifier: Programming Language :: Python :: 3.11
Classifier: Programming Language :: Python :: 3 :: Only
Classifier: Topic :: Software Development :: Libraries :: Application Frameworks
Classifier: Topic :: Software Development :: Libraries :: Python Modules
Requires-Python: >=3.6
License-File: LICENSE
Requires-Dist: Click>=8.1
Requires-Dist: jinja2>=3.1
Requires-Dist: inflection>=0.5.1
Requires-Dist: rich>=13.3
